{
  "pop_size": 40,
  "n_gen": 50,
  "seed": 42,
  "checkpoint": "C:\\Users\\user\\Desktop\\UTIC GNN\\Physics-Informed ST-GNN\\urban-thermal-gnn\\checkpoints_v2_fixed\\best_model.pt",
  "checkpoint_epoch": 129,
  "checkpoint_val_r2": 0.9964864200326653,
  "total_wall_time_s": 318.9,
  "history": [
    {
      "generation": 1,
      "n_gen": 50,
      "n_feasible": 40,
      "best_utci": 31.0,
      "best_green": 0.0082,
      "elapsed_s": 3.18,
      "pareto_count": 6
    },
    {
      "generation": 2,
      "n_gen": 50,
      "n_feasible": 40,
      "best_utci": 30.96,
      "best_green": 0.0096,
      "elapsed_s": 4.01,
      "pareto_count": 7
    },
    {
      "generation": 3,
      "n_gen": 50,
      "n_feasible": 40,
      "best_utci": 30.92,
      "best_green": 0.0129,
      "elapsed_s": 4.27,
      "pareto_count": 5
    },
    {
      "generation": 4,
      "n_gen": 50,
      "n_feasible": 40,
      "best_utci": 30.9,
      "best_green": 0.0178,
      "elapsed_s": 4.42,
      "pareto_count": 4
    },
    {
      "generation": 5,
      "n_gen": 50,
      "n_feasible": 40,
      "best_utci": 30.9,
      "best_green": 0.0178,
      "elapsed_s": 4.5,
      "pareto_count": 4
    },
    {
      "generation": 6,
      "n_gen": 50,
      "n_feasible": 40,
      "best_utci": 30.9,
      "best_green": 0.0177,
      "elapsed_s": 4.72,
      "pareto_count": 8
    },
    {
      "generation": 7,
      "n_gen": 50,
      "n_feasible": 40,
      "best_utci": 30.9,
      "best_green": 0.0203,
      "elapsed_s": 4.24,
      "pareto_count": 12
    },
    {
      "generation": 8,
      "n_gen": 50,
      "n_feasible": 40,
      "best_utci": 30.9,
      "best_green": 0.0203,
      "elapsed_s": 4.03,
      "pareto_count": 13
    },
    {
      "generation": 9,
      "n_gen": 50,
      "n_feasible": 40,
      "best_utci": 30.89,
      "best_green": 0.0128,
      "elapsed_s": 4.52,
      "pareto_count": 13
    },
    {
      "generation": 10,
      "n_gen": 50,
      "n_feasible": 40,
      "best_utci": 30.89,
      "best_green": 0.0128,
      "elapsed_s": 4.81,
      "pareto_count": 19
    },
    {
      "generation": 11,
      "n_gen": 50,
      "n_feasible": 40,
      "best_utci": 30.89,
      "best_green": 0.0128,
      "elapsed_s": 5.0,
      "pareto_count": 12
    },
    {
      "generation": 12,
      "n_gen": 50,
      "n_feasible": 40,
      "best_utci": 30.89,
      "best_green": 0.0128,
      "elapsed_s": 6.34,
      "pareto_count": 14
    },
    {
      "generation": 13,
      "n_gen": 50,
      "n_feasible": 40,
      "best_utci": 30.89,
      "best_green": 0.0128,
      "elapsed_s": 4.51,
      "pareto_count": 16
    },
    {
      "generation": 14,
      "n_gen": 50,
      "n_feasible": 40,
      "best_utci": 30.89,
      "best_green": 0.0124,
      "elapsed_s": 4.23,
      "pareto_count": 8
    },
    {
      "generation": 15,
      "n_gen": 50,
      "n_feasible": 40,
      "best_utci": 30.89,
      "best_green": 0.0124,
      "elapsed_s": 4.98,
      "pareto_count": 12
    },
    {
      "generation": 16,
      "n_gen": 50,
      "n_feasible": 40,
      "best_utci": 30.89,
      "best_green": 0.0124,
      "elapsed_s": 6.6,
      "pareto_count": 7
    },
    {
      "generation": 17,
      "n_gen": 50,
      "n_feasible": 40,
      "best_utci": 30.88,
      "best_green": 0.0119,
      "elapsed_s": 6.31,
      "pareto_count": 15
    },
    {
      "generation": 18,
      "n_gen": 50,
      "n_feasible": 40,
      "best_utci": 30.88,
      "best_green": 0.0119,
      "elapsed_s": 5.22,
      "pareto_count": 17
    },
    {
      "generation": 19,
      "n_gen": 50,
      "n_feasible": 40,
      "best_utci": 30.88,
      "best_green": 0.0119,
      "elapsed_s": 4.53,
      "pareto_count": 11
    },
    {
      "generation": 20,
      "n_gen": 50,
      "n_feasible": 40,
      "best_utci": 30.88,
      "best_green": 0.0118,
      "elapsed_s": 4.5,
      "pareto_count": 10
    },
    {
      "generation": 21,
      "n_gen": 50,
      "n_feasible": 40,
      "best_utci": 30.88,
      "best_green": 0.0118,
      "elapsed_s": 4.57,
      "pareto_count": 10
    },
    {
      "generation": 22,
      "n_gen": 50,
      "n_feasible": 40,
      "best_utci": 30.88,
      "best_green": 0.0118,
      "elapsed_s": 6.75,
      "pareto_count": 5
    },
    {
      "generation": 23,
      "n_gen": 50,
      "n_feasible": 40,
      "best_utci": 30.87,
      "best_green": 0.0119,
      "elapsed_s": 7.74,
      "pareto_count": 7
    },
    {
      "generation": 24,
      "n_gen": 50,
      "n_feasible": 40,
      "best_utci": 30.87,
      "best_green": 0.0282,
      "elapsed_s": 5.37,
      "pareto_count": 13
    },
    {
      "generation": 25,
      "n_gen": 50,
      "n_feasible": 40,
      "best_utci": 30.87,
      "best_green": 0.0282,
      "elapsed_s": 4.45,
      "pareto_count": 11
    },
    {
      "generation": 26,
      "n_gen": 50,
      "n_feasible": 40,
      "best_utci": 30.87,
      "best_green": 0.0282,
      "elapsed_s": 6.2,
      "pareto_count": 10
    },
    {
      "generation": 27,
      "n_gen": 50,
      "n_feasible": 40,
      "best_utci": 30.87,
      "best_green": 0.0282,
      "elapsed_s": 11.41,
      "pareto_count": 8
    },
    {
      "generation": 28,
      "n_gen": 50,
      "n_feasible": 40,
      "best_utci": 30.87,
      "best_green": 0.0281,
      "elapsed_s": 8.24,
      "pareto_count": 5
    },
    {
      "generation": 29,
      "n_gen": 50,
      "n_feasible": 40,
      "best_utci": 30.86,
      "best_green": 0.0386,
      "elapsed_s": 7.16,
      "pareto_count": 6
    },
    {
      "generation": 30,
      "n_gen": 50,
      "n_feasible": 40,
      "best_utci": 30.86,
      "best_green": 0.0475,
      "elapsed_s": 8.73,
      "pareto_count": 8
    },
    {
      "generation": 31,
      "n_gen": 50,
      "n_feasible": 40,
      "best_utci": 30.86,
      "best_green": 0.0475,
      "elapsed_s": 9.36,
      "pareto_count": 12
    },
    {
      "generation": 32,
      "n_gen": 50,
      "n_feasible": 40,
      "best_utci": 30.86,
      "best_green": 0.0474,
      "elapsed_s": 7.01,
      "pareto_count": 12
    },
    {
      "generation": 33,
      "n_gen": 50,
      "n_feasible": 40,
      "best_utci": 30.86,
      "best_green": 0.0474,
      "elapsed_s": 7.3,
      "pareto_count": 6
    },
    {
      "generation": 34,
      "n_gen": 50,
      "n_feasible": 40,
      "best_utci": 30.86,
      "best_green": 0.0474,
      "elapsed_s": 10.22,
      "pareto_count": 6
    },
    {
      "generation": 35,
      "n_gen": 50,
      "n_feasible": 40,
      "best_utci": 30.86,
      "best_green": 0.0474,
      "elapsed_s": 8.32,
      "pareto_count": 9
    },
    {
      "generation": 36,
      "n_gen": 50,
      "n_feasible": 40,
      "best_utci": 30.86,
      "best_green": 0.0488,
      "elapsed_s": 6.73,
      "pareto_count": 16
    },
    {
      "generation": 37,
      "n_gen": 50,
      "n_feasible": 40,
      "best_utci": 30.86,
      "best_green": 0.049,
      "elapsed_s": 7.96,
      "pareto_count": 19
    },
    {
      "generation": 38,
      "n_gen": 50,
      "n_feasible": 40,
      "best_utci": 30.85,
      "best_green": 0.049,
      "elapsed_s": 11.18,
      "pareto_count": 20
    },
    {
      "generation": 39,
      "n_gen": 50,
      "n_feasible": 40,
      "best_utci": 30.85,
      "best_green": 0.049,
      "elapsed_s": 8.32,
      "pareto_count": 14
    },
    {
      "generation": 40,
      "n_gen": 50,
      "n_feasible": 40,
      "best_utci": 30.85,
      "best_green": 0.049,
      "elapsed_s": 7.77,
      "pareto_count": 7
    },
    {
      "generation": 41,
      "n_gen": 50,
      "n_feasible": 40,
      "best_utci": 30.85,
      "best_green": 0.049,
      "elapsed_s": 9.97,
      "pareto_count": 7
    },
    {
      "generation": 42,
      "n_gen": 50,
      "n_feasible": 40,
      "best_utci": 30.85,
      "best_green": 0.0489,
      "elapsed_s": 7.28,
      "pareto_count": 5
    },
    {
      "generation": 43,
      "n_gen": 50,
      "n_feasible": 40,
      "best_utci": 30.85,
      "best_green": 0.049,
      "elapsed_s": 7.68,
      "pareto_count": 4
    },
    {
      "generation": 44,
      "n_gen": 50,
      "n_feasible": 40,
      "best_utci": 30.84,
      "best_green": 0.049,
      "elapsed_s": 5.8,
      "pareto_count": 9
    },
    {
      "generation": 45,
      "n_gen": 50,
      "n_feasible": 40,
      "best_utci": 30.84,
      "best_green": 0.0483,
      "elapsed_s": 7.92,
      "pareto_count": 6
    },
    {
      "generation": 46,
      "n_gen": 50,
      "n_feasible": 40,
      "best_utci": 30.84,
      "best_green": 0.0491,
      "elapsed_s": 7.87,
      "pareto_count": 9
    },
    {
      "generation": 47,
      "n_gen": 50,
      "n_feasible": 40,
      "best_utci": 30.84,
      "best_green": 0.0491,
      "elapsed_s": 4.42,
      "pareto_count": 9
    },
    {
      "generation": 48,
      "n_gen": 50,
      "n_feasible": 40,
      "best_utci": 30.84,
      "best_green": 0.0491,
      "elapsed_s": 4.62,
      "pareto_count": 15
    },
    {
      "generation": 49,
      "n_gen": 50,
      "n_feasible": 40,
      "best_utci": 30.84,
      "best_green": 0.0491,
      "elapsed_s": 5.09,
      "pareto_count": 12
    },
    {
      "generation": 50,
      "n_gen": 50,
      "n_feasible": 40,
      "best_utci": 30.84,
      "best_green": 0.0491,
      "elapsed_s": 4.72,
      "pareto_count": 8
    }
  ],
  "final_pareto": [
    {
      "genes": [
        0.0436052722740555,
        0.023245901895913135,
        7.338773669403211e-07,
        0.001144714161651547,
        0.49698466178543876,
        0.05330618910117423,
        0.23605710189961654,
        0.02543556843199236,
        0.00020569258747396048,
        0.011553820649808722,
        0.00010032830888737814,
        5.703076753519167e-05,
        0.23235355656050347,
        0.033827621665202326,
        0.9999746225682018,
        0.028384319295913743,
        0.04397914474805887,
        0.08885507724027299,
        0.9999997810508076,
        0.04405259384880139,
        0.265653428151034,
        0.04751569770455129,
        0.9999871127552542,
        7.79966718853452e-06,
        0.032384220315361895,
        0.22547278798964743,
        0.9999704922738334,
        0.002917827804314021
      ],
      "design": {
        "buildings": [
          {
            "cx": 7.607468044636822,
            "cy": 6.162465472299786,
            "w": 8.000016145302073,
            "d": 8.025183711556334,
            "rot": 89.45723912137898,
            "floors": 2
          },
          {
            "cx": 21.32714431081451,
            "cy": 6.426552069911992,
            "w": 8.004525236924428,
            "d": 8.254184054295791,
            "rot": 0.018059095599728063,
            "floors": 2
          }
        ],
        "trees": [
          {
            "x": 21.26470141397969,
            "y": 7.36785070476,
            "radius": 4.9999111789887065,
            "height": 3.198690235071396
          },
          {
            "x": 8.078539433446334,
            "y": 11.219854776680167,
            "radius": 4.999999233677826,
            "height": 3.3083681569416097
          },
          {
            "x": 23.59571883000099,
            "y": 8.326058020386958,
            "radius": 4.999954894643389,
            "height": 3.00005459767032
          },
          {
            "x": 7.266798834126686,
            "y": 20.783038454558742,
            "radius": 4.999896722958416,
            "height": 3.0204247946301983
          }
        ]
      },
      "mean_utci": 30.84,
      "green_ratio": 0.0491,
      "far": 0.041,
      "bcr": 0.02,
      "violation": 0.0
    },
    {
      "genes": [
        0.04439706897222687,
        0.023256972737321573,
        0.0,
        0.0015057369247612109,
        0.49698466178543876,
        0.08226760868168273,
        0.23625625286173552,
        0.025446303895897242,
        0.000455165859665832,
        0.01155310025961458,
        0.0067979375559491535,
        1.036589431646069e-05,
        0.23194169317493316,
        0.035372349905630096,
        0.9999821854685884,
        0.0016416741277240866,
        0.04394205891610122,
        0.08946002308847499,
        1.0,
        0.06983217260218955,
        0.265653428151034,
        0.04169406197084727,
        0.9999997522025236,
        0.008678295045824973,
        0.041377115800637576,
        0.22479109478373416,
        0.9999995267635835,
        0.0029179736108559833
      ],
      "design": {
        "buildings": [
          {
            "cx": 7.667284296466224,
            "cy": 6.167037755104813,
            "w": 8.0,
            "d": 8.033126212344747,
            "rot": 89.45723912137898,
            "floors": 2
          },
          {
            "cx": 21.341229228160987,
            "cy": 6.427304038061254,
            "w": 8.010013648912649,
            "d": 8.25416820571152,
            "rot": 1.2236287600708475,
            "floors": 2
          }
        ],
        "trees": [
          {
            "x": 21.235885094913428,
            "y": 7.476006553527036,
            "radius": 4.99993764914006,
            "height": 3.0114917188940686
          },
          {
            "x": 8.075944124127085,
            "y": 11.262201616193249,
            "radius": 5.0,
            "height": 3.488825208215327
          },
          {
            "x": 23.595739564078954,
            "y": 7.918583542989925,
            "radius": 4.999999132708833,
            "height": 3.060748065320775
          },
          {
            "x": 7.896396586785279,
            "y": 20.735375723189257,
            "radius": 4.999998343672543,
            "height": 3.020425815275992
          }
        ]
      },
      "mean_utci": 30.84,
      "green_ratio": 0.0491,
      "far": 0.041,
      "bcr": 0.02,
      "violation": 0.0
    },
    {
      "genes": [
        0.0436052722740555,
        0.02326381883649451,
        3.005201210275893e-05,
        0.0015057369247612109,
        0.49698466178543876,
        0.05278027193109611,
        0.23605710189961654,
        0.025446303895897242,
        0.000455165859665832,
        0.011553820649808722,
        0.006803767443072643,
        5.703076753519167e-05,
        0.23235355656050347,
        0.035560604682701814,
        0.9999746225682018,
        0.0017162295258299329,
        0.04397914474805887,
        0.08885507724027299,
        0.9999999013173944,
        0.04606039427385115,
        0.265653428151034,
        0.043099598687364626,
        0.9999890164682639,
        7.79966718853452e-06,
        0.041513570436200894,
        0.22479131972845073,
        0.9999698269881316,
        0.002917827804314021
      ],
      "design": {
        "buildings": [
          {
            "cx": 7.6110929601216135,
            "cy": 6.167523601360757,
            "w": 8.00066114426626,
            "d": 8.033126212344747,
            "rot": 89.45723912137898,
            "floors": 2
          },
          {
            "cx": 21.32714431081451,
            "cy": 6.4273115590654974,
            "w": 8.010013648912649,
            "d": 8.254184054295791,
            "rot": 1.2246781397530757,
            "floors": 2
          }
        ],
        "trees": [
          {
            "x": 21.26470141397969,
            "y": 7.489159823835573,
            "radius": 4.9999111789887065,
            "height": 3.0120136066808096
          },
          {
            "x": 8.078539817354837,
            "y": 11.219855122809143,
            "radius": 4.99999965461088,
            "height": 3.3224227599169582
          },
          {
            "x": 23.59572195290131,
            "y": 8.016936779455117,
            "radius": 4.999961557638923,
            "height": 3.00005459767032
          },
          {
            "x": 7.905853093118697,
            "y": 20.735334253868118,
            "radius": 4.999894394458461,
            "height": 3.0204247946301983
          }
        ]
      },
      "mean_utci": 30.84,
      "green_ratio": 0.0491,
      "far": 0.041,
      "bcr": 0.02,
      "violation": 0.0
    },
    {
      "genes": [
        0.04439706897222687,
        0.023928235622149574,
        0.0,
        0.0,
        0.4969848400420683,
        0.08226760868168273,
        0.29017158649036495,
        0.1379138306401213,
        0.000455165859665832,
        0.011768482103440687,
        0.06808051472860435,
        1.137657889507945e-05,
        0.32364550665449515,
        0.14357591529778768,
        0.9999998740457464,
        0.004444317160120499,
        0.04640706806878566,
        0.08946002308847499,
        0.9999999877354033,
        0.06983244379565927,
        0.26636228307675625,
        0.04169406197084727,
        0.9999999995830435,
        0.008678295045824973,
        0.04152200199858079,
        0.22509619500166356,
        0.9999999925414752,
        0.0029222026959639987
      ],
      "design": {
        "buildings": [
          {
            "cx": 7.652191897028108,
            "cy": 6.19890472917262,
            "w": 8.0,
            "d": 8.0,
            "rot": 89.45727120757229,
            "floors": 2
          },
          {
            "cx": 25.1565086032579,
            "cy": 14.385628476736944,
            "w": 8.010013648912649,
            "d": 8.258906606275696,
            "rot": 12.254492651148784,
            "floors": 2
          }
        ],
        "trees": [
          {
            "x": 27.65518531032647,
            "y": 15.05031375659323,
            "radius": 4.999999559160113,
            "height": 3.0311102201208433
          },
          {
            "x": 8.248494725873055,
            "y": 11.2622015809475,
            "radius": 4.9999999570739115,
            "height": 3.488827106569615
          },
          {
            "x": 23.645359814691016,
            "y": 7.918584336621652,
            "radius": 4.999999998540652,
            "height": 3.060748065320775
          },
          {
            "x": 7.906540115963669,
            "y": 20.756733635763815,
            "radius": 4.999999973895163,
            "height": 3.020455418871748
          }
        ]
      },
      "mean_utci": 30.85,
      "green_ratio": 0.0491,
      "far": 0.041,
      "bcr": 0.02,
      "violation": 0.0
    },
    {
      "genes": [
        0.06909856468918575,
        0.050385719188469104,
        1.531082342761376e-06,
        0.0011452053832729896,
        0.4969796798820816,
        0.07942817865175934,
        0.28901633091171086,
        0.02543562792522321,
        0.004689626467132724,
        0.011553095705681547,
        0.00632435910324881,
        0.0,
        0.2104592547612937,
        0.1481783689508155,
        0.9999999445230316,
        0.03407775207017484,
        0.0007160730596681673,
        0.06236083372873118,
        0.9999997816578704,
        0.06979152828196317,
        0.24534344783414902,
        0.29154283311211215,
        0.9999999944654325,
        0.001627433584153167,
        0.03238702854956399,
        0.22509545366556147,
        0.9999995461406649,
        0.0012964129194962364
      ],
      "design": {
        "buildings": [
          {
            "cx": 9.416854447086504,
            "cy": 8.088713877666505,
            "w": 8.000033683811541,
            "d": 8.025194518432006,
            "rot": 89.45634237877468,
            "floors": 2
          },
          {
            "cx": 25.07378481420035,
            "cy": 6.426548710090752,
            "w": 8.10317178227692,
            "d": 8.254168105524993,
            "rot": 1.1383846385847858,
            "floors": 2
          }
        ],
        "trees": [
          {
            "x": 19.73214772085066,
            "y": 15.3724856899311,
            "radius": 4.999999805830611,
            "height": 3.2385442644912237
          },
          {
            "x": 5.050124351073761,
            "y": 9.36525769212571,
            "radius": 4.999999235802546,
            "height": 3.4885406979737423
          },
          {
            "x": 22.174041338524535,
            "y": 25.40799830977181,
            "radius": 4.999999980629013,
            "height": 3.0113920350890724
          },
          {
            "x": 7.2670905128558925,
            "y": 20.75668088321334,
            "radius": 4.999998411492327,
            "height": 3.0090748904364735
          }
        ]
      },
      "mean_utci": 30.85,
      "green_ratio": 0.0491,
      "far": 0.041,
      "bcr": 0.02,
      "violation": 0.0
    },
    {
      "genes": [
        0.045256877104092395,
        0.025421085091175036,
        0.0,
        0.001533975000947481,
        0.49698466178543876,
        0.08221204284627934,
        0.28425724033280575,
        0.025446303895897242,
        0.000455165859665832,
        0.011553099488666103,
        0.0076240464146020695,
        0.00010113618100651809,
        0.32358090166514425,
        0.03251083565124744,
        1.0,
        0.0026923865472195073,
        0.04556642175401432,
        0.06215309027418185,
        0.9999999110134755,
        0.06837539132196502,
        0.2656610060759161,
        0.041687842250543845,
        0.999998880415141,
        0.008679778169011259,
        0.04137772375001448,
        0.22507314231253014,
        0.9999995264401595,
        0.0029139386121209004
      ],
      "design": {
        "buildings": [
          {
            "cx": 7.728584695202812,
            "cy": 6.32091286968526,
            "w": 8.0,
            "d": 8.033747450020845,
            "rot": 89.45723912137898,
            "floors": 2
          },
          {
            "cx": 24.73709901008988,
            "cy": 6.427304030012412,
            "w": 8.010013648912649,
            "d": 8.254168188750654,
            "rot": 1.3723283546283724,
            "floors": 2
          }
        ],
        "trees": [
          {
            "x": 27.650663116560096,
            "y": 7.27575849558732,
            "radius": 5.0,
            "height": 3.0188467058305366
          },
          {
            "x": 8.18964923971175,
            "y": 9.350716046455407,
            "radius": 4.999999688547165,
            "height": 3.478627739253755
          },
          {
            "x": 23.5962685887774,
            "y": 7.9181453657026015,
            "radius": 4.999996081452993,
            "height": 3.060758447183079
          },
          {
            "x": 7.896439142205369,
            "y": 20.755119050516875,
            "radius": 4.999998342540558,
            "height": 3.0203975702848465
          }
        ]
      },
      "mean_utci": 30.85,
      "green_ratio": 0.0491,
      "far": 0.041,
      "bcr": 0.02,
      "violation": 0.0
    },
    {
      "genes": [
        0.04361383236563872,
        0.023928235622149574,
        0.00018161199566028852,
        0.0015057324223859746,
        0.49698466178052014,
        0.08223160296655964,
        0.2849990070551776,
        0.025446303895897242,
        0.0004548638657809661,
        0.011553852713605135,
        0.00712682218160655,
        1.137657889507945e-05,
        0.3233751873156341,
        0.035372349905630096,
        0.9999821704232097,
        0.004487267180695385,
        0.043889576219739095,
        0.03771667627560204,
        1.0,
        0.07036267939469616,
        0.265653428151034,
        0.04309341884062873,
        0.9999997522025236,
        0.008678295045824973,
        0.041377115800637576,
        0.2250602745955507,
        0.9999997785523252,
        0.002922176611917069
      ],
      "design": {
        "buildings": [
          {
            "cx": 7.611700397854531,
            "cy": 6.2146751363747565,
            "w": 8.003995463904527,
            "d": 8.033126113292491,
            "rot": 89.45723912049363,
            "floors": 2
          },
          {
            "cx": 24.789579476644406,
            "cy": 6.427311893817347,
            "w": 8.010007005047182,
            "d": 8.254184759699314,
            "rot": 1.282827992689179,
            "floors": 2
          }
        ],
        "trees": [
          {
            "x": 27.63624106807476,
            "y": 7.476006504593542,
            "radius": 4.999937596481233,
            "height": 3.031410870264868
          },
          {
            "x": 8.072270335381736,
            "y": 7.640167339292143,
            "radius": 5.0,
            "height": 3.4925387557628733
          },
          {
            "x": 23.595739564078954,
            "y": 8.016538526301927,
            "radius": 4.999999132708833,
            "height": 3.060748065320775
          },
          {
            "x": 7.89639739511783,
            "y": 20.75421879549521,
            "radius": 4.999999224933138,
            "height": 3.0204552362834196
          }
        ]
      },
      "mean_utci": 30.85,
      "green_ratio": 0.0491,
      "far": 0.041,
      "bcr": 0.02,
      "violation": 0.0
    },
    {
      "genes": [
        0.04525212262712893,
        0.025391497425423598,
        0.00013838615923421728,
        0.0015295342757121236,
        0.4969846291417805,
        0.08221204284627934,
        0.28779587756977293,
        0.025446303895897242,
        0.00045671522988287354,
        0.011756621878837845,
        0.0076230173140353795,
        0.00010247412636180751,
        0.32240397685078453,
        0.031666178163159364,
        1.0,
        0.002715301949286605,
        0.045551917444221185,
        0.08792261777718302,
        0.9999996571211731,
        0.06837539132196502,
        0.2656610060759161,
        0.041687842250543845,
        0.999998880415141,
        0.008679778169011259,
        0.04137772375001448,
        0.22507314231253014,
        0.9999995264401595,
        0.002978343455187144
      ],
      "design": {
        "buildings": [
          {
            "cx": 7.728202860761636,
            "cy": 6.318766776594185,
            "w": 8.003044495503152,
            "d": 8.033649754065667,
            "rot": 89.45723324552048,
            "floors": 2
          },
          {
            "cx": 24.98839298728182,
            "cy": 6.429428840667323,
            "w": 8.010047735057423,
            "d": 8.258645681334432,
            "rot": 1.3721431165263682,
            "floors": 2
          }
        ],
        "trees": [
          {
            "x": 27.56827837955492,
            "y": 7.216632471421155,
            "radius": 5.0,
            "height": 3.019007113645006
          },
          {
            "x": 8.188633130351105,
            "y": 11.154582255354546,
            "radius": 4.999998799924105,
            "height": 3.478627739253755
          },
          {
            "x": 23.5962685887774,
            "y": 7.9181453657026015,
            "radius": 4.999996081452993,
            "height": 3.060758447183079
          },
          {
            "x": 7.896439142205369,
            "y": 20.755119050516875,
            "radius": 4.999998342540558,
            "height": 3.02084840418631
          }
        ]
      },
      "mean_utci": 30.85,
      "green_ratio": 0.0491,
      "far": 0.041,
      "bcr": 0.02,
      "violation": 0.0
    }
  ],
  "status": "complete"
}